numdata/__init__.py
numdata/calculate.py
numdatasalva/__init__.py
numdatasalva/calculate.py
numdatasalva-0.0.5.dist-info/LICENSE
numdatasalva-0.0.5.dist-info/METADATA
numdatasalva-0.0.5.dist-info/WHEEL
numdatasalva-0.0.5.dist-info/top_level.txt
numdatasalva-0.0.5.dist-info/RECORD
