Metadata-Version: 2.1
Name: numdatasalva
Version: 0.0.5
Summary: A simple package calculating values for a simple number
Home-page: UNKNOWN
Author: Salvador Gimeno
Author-email: Salvador.Gimeno@xyz.com
License: UNKNOWN
Keywords: numbers package calculations
Platform: UNKNOWN
Classifier: Programming Language :: Python :: 2
Classifier: Development Status :: 3 - Alpha
Classifier: Intended Audience :: Developers
Classifier: Topic :: Software Development :: Build Tools
Classifier: License :: OSI Approved :: MIT License
Classifier: Programming Language :: Python :: 2
Classifier: Programming Language :: Python :: 2.6
Classifier: Programming Language :: Python :: 2.7
Classifier: Programming Language :: Python :: 3
Classifier: Programming Language :: Python :: 3.2
Classifier: Programming Language :: Python :: 3.3
Classifier: Programming Language :: Python :: 3.4
